lda_classification/__init__.py
lda_classification/data/__init__.py
lda_classification/data/datatypes.py
lda_classification/data/reader.py
lda_classification/evaluation/__init__.py
lda_classification/evaluation/lda_coherence_evaluation.py
lda_classification/model/__init__.py
lda_classification/model/gensim_lda_vectorizer.py
lda_classification/model/tomotopy_lda_vectorizer.py
lda_classification/preprocess/__init__.py
lda_classification/preprocess/base.py
lda_classification/preprocess/gensim_cleaner.py
lda_classification/preprocess/spacy_cleaner.py
lda_classification/utils/__init__.py
lda_classification/utils/model_selection/__init__.py
lda_classification/utils/model_selection/xgboost_features.py
lda_classification-0.0.29.dist-info/LICENSE
lda_classification-0.0.29.dist-info/METADATA
lda_classification-0.0.29.dist-info/WHEEL
lda_classification-0.0.29.dist-info/top_level.txt
lda_classification-0.0.29.dist-info/RECORD
