Metadata-Version: 2.1
Name: lda-classification
Version: 0.0.29
Summary: UNKNOWN
Home-page: https://github.com/FeryET/lda_classification
Author: Farhood Etaati
Author-email: farhoodet@gmail.com
License: UNKNOWN
Platform: UNKNOWN
Classifier: Programming Language :: Python :: 3
Classifier: License :: OSI Approved :: MIT License
Classifier: Operating System :: OS Independent
Requires-Python: >=3.5
Requires-Dist: gensim (~=3.8.0)
Requires-Dist: matplotlib (>=3.1.2)
Requires-Dist: numpy (~=1.19.1)
Requires-Dist: setuptools (~=49.6.0)
Requires-Dist: spacy (~=2.3.1)
Requires-Dist: tqdm (~=4.48.2)
Requires-Dist: scikit-learn (~=0.23.1)
Requires-Dist: tomotopy (~=0.9.1)
